{"Company": {"?": {"Company": {"?": 1176}}, "a&w": {"Company": {"a&w": 3846}, "Description": {" avec louis": 1293}}, "adaptateur": {"Company": {"adaptateur": 1176}}, "amazon": {"Company": {"amazon": 11052}, "Description": {" balance et mixeur": 1176, " barres cereales testees fin marathon, nouveau test": 1293, " brassard course": 1176, " jeu d echec": 1176, " livre": 1293, " livres cours": 1176, " livres de cours": 1293, " pompe velo": 1293, " raquette ping pong": 1176}}, "archambault": {"Company": {"archambault": 1293}, "Description": {" livres": 1293}}, "avion": {"Company": {"avion": 2265}, "Description": {" billet france -> quebec": 972, " voyage a chicago": 1293}}, "bar": {"Company": {"bar": 1176}, "Description": {" metre biere": 1176}}, "best buy": {"Company": {"best buy": 1293}, "Description": {" clavier qwerty": 1293}}, "boulangerie": {"Company": {"boulangerie": 1293}, "Description": {" pains au raisin": 1293}}, "bus": {"Company": {"bus": 4938}, "Description": {" payment du semestre": 1293, " ticket aller retour": 1293}}, "busbud": {"Company": {"busbud": 1176}, "Description": {" bus aller retour newyork; ny.19.10": 1176}}, "cafe ": {"Company": {"cafe ": 1291}}, "cafe au temps perdu": {"Company": {"cafe au temps perdu": 1293}, "Description": {" date avec ellie": 1293}}, "campus laval": {"Company": {"campus laval": 6348}, "Description": {" loyer": 3879, " loyer residence": 1293, " payement des loyers de oct., nov. et dec.": 1176}}, "campus laval ": {"Company": {"campus laval ": 972}, "Description": {" 1er loyer du campus laval": 972}}, "casino": {"Company": {"casino": 972}}, "chalet": {"Company": {"chalet": 1293}, "Description": {" avance mcdo": 1293}}, "chez alphonse": {"Company": {"chez alphonse": 7641}, "Description": {" fruits secs": 6465, " provision depart baleines": 1176}}, "chipotle": {"Company": {"chipotle": 1253}}, "cine": {"Company": {"cine": 1176}, "Description": {" ca": 1176}}, "cinema": {"Company": {"cinema": 1293}, "Description": {" star wars": 1293}}, "cite medicale": {"Company": {"cite medicale": 1293}, "Description": {" ostheopathie": 1293}}, "clap": {"Company": {"clap": 1293}, "Description": {" film 1917": 1293}}, "clinique dentaire trudel b": {"Company": {"clinique dentaire trudel b": 1293}, "Description": {" dentiste": 1293}}, "coiffeur": {"Company": {"coiffeur": 3879}, "Description": {" coupe de cheveux": 1293}}, "coiffeur cite": {"Company": {"coiffeur cite": 1176}, "Description": {" gomme": 1176}}, "coinomatic": {"Company": {"coinomatic": 5053}, "Description": {" argent pour machine a laver": 5053}}, "coop zone": {"Company": {"coop zone": 7641}, "Description": {" aaptateur prise americaine": 1293, " achat cle usb 64go": 1293, " feuilles cahier": 1176, " livres et piles": 1293, " materiel scolaire": 1293, " papier": 1293}}, "creuset": {"Company": {"creuset": 1176}, "Description": {" casserole et poele": 1176}}, "cvec": {"Company": {"cvec": 1176}, "Description": {" inscription ensea": 1176}}, "decathlon": {"Company": {"decathlon": 2469}, "Description": {" balle gym, tapis, patins a glace": 1293, " thermos": 1176}}, "delaware north": {"Company": {"delaware north": 1293}, "Description": {" burger": 1293}}, "dell": {"Company": {"dell": 1293}, "Description": {" achat pc portable au detaillant": 1293}}, "dentiste": {"Company": {"dentiste": 1293}, "Description": {" dent cassee en patinant": 1293}}, "desjardin": {"Company": {"desjardin": 1293}, "Description": {" assurance maladie et hospitalisation": 1293}}, "desjardins": {"Company": {"desjardins": 1176}, "Description": {" marathon quebec": 1176}}, "discount": {"Company": {"discount": 1293}, "Description": {" location voiture": 1293}}, "dollarama": {"Company": {"dollarama": 6114}, "Description": {" panier pour rangement": 1293, " paniers": 1176, " paniers pour ranger": 1293, " plats en verre": 1176}}, "domino s": {"Company": {"domino s": 2586}, "Description": {" pizza": 2586}}, "dunkin  donuts": {"Company": {"dunkin  donuts": 1293}, "Description": {" donuts": 1293}}, "ensea": {"Company": {"ensea": 1176}, "Description": {" inscription": 1176}}, "epicerie europeenne": {"Company": {"epicerie europeenne": 11637}, "Description": {" avance pour le repas de noel": 1293, " courses": 6465, " the et biscuits": 1293, " the et gingembre": 1293, " the, fromage et gingembre": 1293}}, "escompte": {"Company": {"escompte": 1176}, "Description": {" biere": 1176}}, "esta": {"Company": {"esta": 1176}}, "five guys": {"Company": {"five guys": 3879}, "Description": {" midi": 1293, " milkshake": 1293, " restaurant": 1293}}, "franprix": {"Company": {"franprix": 972}}, "frisson": {"Company": {"frisson": 7407}, "Description": {" glace": 3645, " glace 2 boules": 1176, " glaces": 2586}}, "globo chaussures": {"Company": {"globo chaussures": 1293}, "Description": {" chaussures geox de ville": 1293}}, "h&m": {"Company": {"h&m": 2352}, "Description": {" 2 t-shirt": 1176, " vetements haut": 1176}}, "iga": {"Company": {"iga": 4821}, "Description": {" courses": 1293, " courses + patisserie": 1176, " cuisine": 1176, " nourriture": 1176}}, "ikea": {"Company": {"ikea": 3879}, "Description": {" hotdogs": 2586, " protege couette, bougies": 1293}}, "imprimante": {"Company": {"imprimante": 1176}}, "indigo": {"Company": {"indigo": 1293}, "Description": {" place de stationnement": 1293}}, "jus jugo juice": {"Company": {"jus jugo juice": 1293}, "Description": {" smoothie": 1293}}, "la place": {"Company": {"la place": 1176}, "Description": {" the et autre": 1176}}, "le crac": {"Company": {"le crac": 3877}, "Description": {" flocon d avoinne, miel et papaye + mangue sechee": 1293, " flocon d avoinne, noix et echalotte": 1293, " flocon d avoinne, papaye + mangue sechee": 1291}}, "le creuset": {"Company": {"le creuset": 1176}, "Description": {" gant et protege main cuisine": 1176}}, "leclerc": {"Company": {"leclerc": 972}}, "lettre": {"Company": {"lettre": 1176}}, "levis": {"Company": {"levis": 1176}, "Description": {" 2 jeans, un fonce et un couleur jean": 1176}}, "librairie renaud-bray": {"Company": {"librairie renaud-bray": 1293}, "Description": {" 5 livres": 1293}}, "linge": {"Company": {"linge": 1176}}, "lpu": {"Company": {"lpu": 1176}}, "lvlop": {"Company": {"lvlop": 6112}, "Description": {" aprem gaming": 2584}}, "marche de noel": {"Company": {"marche de noel": 1293}, "Description": {" pain au fromage": 1293}}, "marshalls": {"Company": {"marshalls": 3879}, "Description": {" calecons": 1293, " chaussettes et calecons": 1293, " remboursement calecons": 1293}}, "mary s popcorn": {"Company": {"mary s popcorn": 1293}, "Description": {" popcorn": 1293}}, "mcdo": {"Company": {"mcdo": 14647}, "Description": {" bouffe apres le shackeur": 1293, " rentrant de soiree": 1176, " sundae": 1293, " uber eats": 2429}}, "mec": {"Company": {"mec": 5172}, "Description": {" achat chaussettes hiver": 1293, " chaussures + chaussettes (1 paire chaque)": 1293, " collant et 2 paires de chaussettes hiver": 1293, " remboursement commande": 1293}}, "metro": {"Company": {"metro": 75839}, "Description": {" alimentaire": 1176, " alimentation": 1176, " bananes": 1293, " course et beaucoup pour la cuisine": 1293, " courses": 43691, " courses cuisine": 2469, " courses cuisine et legumes": 1260, " courses cuisine et manger": 1176, " courses et avance pour le repas de noel": 1293, " courses et extra": 2586, " courses legeres": 1293, " courses petit dej et legumes": 1260, " courses pour repas du 31": 1293, " courses pour road trip": 1293, " courses semaine": 1293, " cuisine": 1176, " cuisine et barbecue": 1176, " fruits legumes": 1176, " legume": 1176, " nourriture": 3528, " patisserie": 1293, " preservatifs": 1293, " viande": 1176}}, "murphy s": {"Company": {"murphy s": 1176}, "Description": {" bar": 1176}}, "netflix": {"Company": {"netflix": 2584}, "Description": {" abonnement": 1291}}, "nintendo": {"Company": {"nintendo": 1260}, "Description": {" peluches": 1260}}, "nougat": {"Company": {"nougat": 1293}}, "ovh": {"Company": {"ovh": 1176}, "Description": {" nom domaine": 1176}}, "panda express": {"Company": {"panda express": 2586}, "Description": {" bol": 1293, " manger": 1293}}, "peps": {"Company": {"peps": 5170}, "Description": {" kine": 1291, " nutritionniste": 2586, " piscine": 1293}}, "petro-canada": {"Company": {"petro-canada": 2586}, "Description": {" plein essence": 2586}}, "pfk": {"Company": {"pfk": 1176}, "Description": {" mauvais": 1176}}, "poste": {"Company": {"poste": 6432}, "Description": {" envoi colis amelie et clara": 1260, " lettre pour caq": 1293, " lettre recommandee desabonnement le monde": 1293, " lettres pour noel pour la famille": 1293, " papiers pour permi etude manquants": 1293}}, "poste canada": {"Company": {"poste canada": 1176}, "Description": {" enveloppes blanches": 1176}}, "poutineville": {"Company": {"poutineville": 3645}, "Description": {" grosse poutine": 1176, " tiphanie": 1176}}, "provigo": {"Company": {"provigo": 7750}, "Description": {" courses": 7750}}, "pub st alexandre": {"Company": {"pub st alexandre": 1293}, "Description": {" biere": 1293}}, "pub u": {"Company": {"pub u": 2436}, "Description": {" ailes de poulet": 1260, " ailes de poulet + biere": 1176}}, "pub universitaire": {"Company": {"pub universitaire": 1176}, "Description": {" soiree": 1176}}, "quebec": {"Company": {"quebec": 1293}, "Description": {" caq": 1293}}, "queue de castor": {"Company": {"queue de castor": 1176}, "Description": {" poutine": 1176}}, "ramq": {"Company": {"ramq": 1253}}, "remboursement": {"Company": {"remboursement": 2469}, "Description": {" aurelien logement new york; ny.19.10": 1176}}, "retrait borne": {"Company": {"retrait borne": 1253}, "Description": {" pour le pauvre qui m a indique le chemin": 1253}}, "rhum": {"Company": {"rhum": 1260}}, "rogers": {"Company": {"rogers": 1293}, "Description": {" ligne telephonique": 1293}}, "rtc": {"Company": {"rtc": 2584}, "Description": {" ticket pour le bus": 2584}}, "rudy s bar": {"Company": {"rudy s bar": 1293}, "Description": {" pizza pate chicago": 1293}}, "saq": {"Company": {"saq": 2352}, "Description": {" alcool": 1176, " vodka et kraken (rhum)": 1176}}, "shogun": {"Company": {"shogun": 1176}, "Description": {" japonais a volonter": 1176}}, "shogun sushi": {"Company": {"shogun sushi": 3877}, "Description": {" jap illimite": 1293, " restaurant": 2584}}, "skream": {"Company": {"skream": 1260}, "Description": {" concert boite nuit electro": 1260}}, "sofitel montreal": {"Company": {"sofitel montreal": 1293}, "Description": {" brunch": 1293}}, "sport expert": {"Company": {"sport expert": 5172}, "Description": {" ": 1293, " bas pour la course et gants en merino": 1293, " corde a sauter et chaussettes course": 1293, " short course": 1293}}, "sport experts": {"Company": {"sport experts": 4898}, "Description": {" chaussures et maillot de bain": 1176, " gourde": 1253, " haut coupe vent et calecons": 1293, " sac course": 1176}}, "starbucks": {"Company": {"starbucks": 1260}, "Description": {" cafe + gateau": 1260}}, "steam": {"Company": {"steam": 5172}, "Description": {" dlc crypt": 1293, " jeu video": 1293, " northgard": 1293, " ratropolis": 1293}}, "studio universal": {"Company": {"studio universal": 1293}, "Description": {" souvenirs": 1293}}, "tacobell": {"Company": {"tacobell": 1260}}, "thinkkitchen": {"Company": {"thinkkitchen": 3645}, "Description": {" equipement": 1176, " fouet, passoire": 1176, " plaque pour gateaux": 1293}}, "tim horton": {"Company": {"tim horton": 1291}, "Description": {" donuts": 1291}}, "uber eats": {"Company": {"uber eats": 1293}, "Description": {" mcdo": 1293}}, "univrac": {"Company": {"univrac": 2586}, "Description": {" fruits secs": 1293, " lentilles et amandes": 1293}}, "walmart": {"Company": {"walmart": 15924}, "Description": {" achat lime a ongle, fil dentaire et ciseau ongle": 1293, " balais": 1293, " bouchons oreilles": 1260, " brosse a dents electrique et couette hiver": 1260, " brosse a dents, crocks, rasoirs": 1176, " courses": 1176, " creme, solaire, coussin, lampe": 1176, " draps + oreiller": 1176, " equipement et affaires scolaires": 1293, " equipement papier cuisson ...": 1176, " preservatifs et lubrifiant": 1293, " provision depart baleines": 1176, " tasse, bol, bouilloire, boule a the, manger": 1176}}, "wendy s": {"Company": {"wendy s": 5099}, "Description": {" avance": 1293}}, "world trade center 1": {"Company": {"world trade center 1": 1260}, "Description": {" visite du dernier etage": 1260}}, "yves rocher": {"Company": {"yves rocher": 1176}, "Description": {" masques": 1176}}, "oqkefqef": {"Company": {"oqkefqef": 1}}}}