{"Company": {"?": {"Company": {"?": 1170}}, "a&w": {"Company": {"a&w": 3828}, "Description": {" avec louis": 1287}}, "adaptateur": {"Company": {"adaptateur": 1170}}, "amazon": {"Company": {"amazon": 10998}, "Description": {" balance et mixeur": 1170, " barres cereales testees fin marathon, nouveau test": 1287, " brassard course": 1170, " jeu d echec": 1170, " livre": 1287, " livres cours": 1170, " livres de cours": 1287, " pompe velo": 1287, " raquette ping pong": 1170}}, "archambault": {"Company": {"archambault": 1287}, "Description": {" livres": 1287}}, "avion": {"Company": {"avion": 2253}, "Description": {" billet france -> quebec": 966, " voyage a chicago": 1287}}, "bar": {"Company": {"bar": 1170}, "Description": {" metre biere": 1170}}, "best buy": {"Company": {"best buy": 1287}, "Description": {" clavier qwerty": 1287}}, "boulangerie": {"Company": {"boulangerie": 1287}, "Description": {" pains au raisin": 1287}}, "bus": {"Company": {"bus": 4914}, "Description": {" payment du semestre": 1287, " ticket aller retour": 1287}}, "busbud": {"Company": {"busbud": 1170}, "Description": {" bus aller retour newyork; ny.19.10": 1170}}, "cafe ": {"Company": {"cafe ": 1285}}, "cafe au temps perdu": {"Company": {"cafe au temps perdu": 1287}, "Description": {" date avec ellie": 1287}}, "campus laval": {"Company": {"campus laval": 6318}, "Description": {" loyer": 3861, " loyer residence": 1287, " payement des loyers de oct., nov. et dec.": 1170}}, "campus laval ": {"Company": {"campus laval ": 966}, "Description": {" 1er loyer du campus laval": 966}}, "casino": {"Company": {"casino": 966}}, "chalet": {"Company": {"chalet": 1287}, "Description": {" avance mcdo": 1287}}, "chez alphonse": {"Company": {"chez alphonse": 7605}, "Description": {" fruits secs": 6435, " provision depart baleines": 1170}}, "chipotle": {"Company": {"chipotle": 1247}}, "cine": {"Company": {"cine": 1170}, "Description": {" ca": 1170}}, "cinema": {"Company": {"cinema": 1287}, "Description": {" star wars": 1287}}, "cite medicale": {"Company": {"cite medicale": 1287}, "Description": {" ostheopathie": 1287}}, "clap": {"Company": {"clap": 1287}, "Description": {" film 1917": 1287}}, "clinique dentaire trudel b": {"Company": {"clinique dentaire trudel b": 1287}, "Description": {" dentiste": 1287}}, "coiffeur": {"Company": {"coiffeur": 3861}, "Description": {" coupe de cheveux": 1287}}, "coiffeur cite": {"Company": {"coiffeur cite": 1170}, "Description": {" gomme": 1170}}, "coinomatic": {"Company": {"coinomatic": 5029}, "Description": {" argent pour machine a laver": 5029}}, "coop zone": {"Company": {"coop zone": 7605}, "Description": {" aaptateur prise americaine": 1287, " achat cle usb 64go": 1287, " feuilles cahier": 1170, " livres et piles": 1287, " materiel scolaire": 1287, " papier": 1287}}, "creuset": {"Company": {"creuset": 1170}, "Description": {" casserole et poele": 1170}}, "cvec": {"Company": {"cvec": 1170}, "Description": {" inscription ensea": 1170}}, "decathlon": {"Company": {"decathlon": 2457}, "Description": {" balle gym, tapis, patins a glace": 1287, " thermos": 1170}}, "delaware north": {"Company": {"delaware north": 1287}, "Description": {" burger": 1287}}, "dell": {"Company": {"dell": 1287}, "Description": {" achat pc portable au detaillant": 1287}}, "dentiste": {"Company": {"dentiste": 1287}, "Description": {" dent cassee en patinant": 1287}}, "desjardin": {"Company": {"desjardin": 1287}, "Description": {" assurance maladie et hospitalisation": 1287}}, "desjardins": {"Company": {"desjardins": 1170}, "Description": {" marathon quebec": 1170}}, "discount": {"Company": {"discount": 1287}, "Description": {" location voiture": 1287}}, "dollarama": {"Company": {"dollarama": 6084}, "Description": {" panier pour rangement": 1287, " paniers": 1170, " paniers pour ranger": 1287, " plats en verre": 1170}}, "domino s": {"Company": {"domino s": 2574}, "Description": {" pizza": 2574}}, "dunkin  donuts": {"Company": {"dunkin  donuts": 1287}, "Description": {" donuts": 1287}}, "ensea": {"Company": {"ensea": 1170}, "Description": {" inscription": 1170}}, "epicerie europeenne": {"Company": {"epicerie europeenne": 11583}, "Description": {" avance pour le repas de noel": 1287, " courses": 6435, " the et biscuits": 1287, " the et gingembre": 1287, " the, fromage et gingembre": 1287}}, "escompte": {"Company": {"escompte": 1170}, "Description": {" biere": 1170}}, "esta": {"Company": {"esta": 1170}}, "five guys": {"Company": {"five guys": 3861}, "Description": {" midi": 1287, " milkshake": 1287, " restaurant": 1287}}, "franprix": {"Company": {"franprix": 966}}, "frisson": {"Company": {"frisson": 7371}, "Description": {" glace": 3627, " glace 2 boules": 1170, " glaces": 2574}}, "globo chaussures": {"Company": {"globo chaussures": 1287}, "Description": {" chaussures geox de ville": 1287}}, "h&m": {"Company": {"h&m": 2340}, "Description": {" 2 t-shirt": 1170, " vetements haut": 1170}}, "iga": {"Company": {"iga": 4797}, "Description": {" courses": 1287, " courses + patisserie": 1170, " cuisine": 1170, " nourriture": 1170}}, "ikea": {"Company": {"ikea": 3861}, "Description": {" hotdogs": 2574, " protege couette, bougies": 1287}}, "imprimante": {"Company": {"imprimante": 1170}}, "indigo": {"Company": {"indigo": 1287}, "Description": {" place de stationnement": 1287}}, "jus jugo juice": {"Company": {"jus jugo juice": 1287}, "Description": {" smoothie": 1287}}, "la place": {"Company": {"la place": 1170}, "Description": {" the et autre": 1170}}, "le crac": {"Company": {"le crac": 3859}, "Description": {" flocon d avoinne, miel et papaye + mangue sechee": 1287, " flocon d avoinne, noix et echalotte": 1287, " flocon d avoinne, papaye + mangue sechee": 1285}}, "le creuset": {"Company": {"le creuset": 1170}, "Description": {" gant et protege main cuisine": 1170}}, "leclerc": {"Company": {"leclerc": 966}}, "lettre": {"Company": {"lettre": 1170}}, "levis": {"Company": {"levis": 1170}, "Description": {" 2 jeans, un fonce et un couleur jean": 1170}}, "librairie renaud-bray": {"Company": {"librairie renaud-bray": 1287}, "Description": {" 5 livres": 1287}}, "linge": {"Company": {"linge": 1170}}, "lpu": {"Company": {"lpu": 1170}}, "lvlop": {"Company": {"lvlop": 6082}, "Description": {" aprem gaming": 2572}}, "marche de noel": {"Company": {"marche de noel": 1287}, "Description": {" pain au fromage": 1287}}, "marshalls": {"Company": {"marshalls": 3861}, "Description": {" calecons": 1287, " chaussettes et calecons": 1287, " remboursement calecons": 1287}}, "mary s popcorn": {"Company": {"mary s popcorn": 1287}, "Description": {" popcorn": 1287}}, "mcdo": {"Company": {"mcdo": 14575}, "Description": {" bouffe apres le shackeur": 1287, " rentrant de soiree": 1170, " sundae": 1287, " uber eats": 2417}}, "mec": {"Company": {"mec": 5148}, "Description": {" achat chaussettes hiver": 1287, " chaussures + chaussettes (1 paire chaque)": 1287, " collant et 2 paires de chaussettes hiver": 1287, " remboursement commande": 1287}}, "metro": {"Company": {"metro": 75479}, "Description": {" alimentaire": 1170, " alimentation": 1170, " bananes": 1287, " course et beaucoup pour la cuisine": 1287, " courses": 43487, " courses cuisine": 2457, " courses cuisine et legumes": 1254, " courses cuisine et manger": 1170, " courses et avance pour le repas de noel": 1287, " courses et extra": 2574, " courses legeres": 1287, " courses petit dej et legumes": 1254, " courses pour repas du 31": 1287, " courses pour road trip": 1287, " courses semaine": 1287, " cuisine": 1170, " cuisine et barbecue": 1170, " fruits legumes": 1170, " legume": 1170, " nourriture": 3510, " patisserie": 1287, " preservatifs": 1287, " viande": 1170}}, "murphy s": {"Company": {"murphy s": 1170}, "Description": {" bar": 1170}}, "netflix": {"Company": {"netflix": 2572}, "Description": {" abonnement": 1285}}, "nintendo": {"Company": {"nintendo": 1254}, "Description": {" peluches": 1254}}, "nougat": {"Company": {"nougat": 1287}}, "ovh": {"Company": {"ovh": 1170}, "Description": {" nom domaine": 1170}}, "panda express": {"Company": {"panda express": 2574}, "Description": {" bol": 1287, " manger": 1287}}, "peps": {"Company": {"peps": 5146}, "Description": {" kine": 1285, " nutritionniste": 2574, " piscine": 1287}}, "petro-canada": {"Company": {"petro-canada": 2574}, "Description": {" plein essence": 2574}}, "pfk": {"Company": {"pfk": 1170}, "Description": {" mauvais": 1170}}, "poste": {"Company": {"poste": 6402}, "Description": {" envoi colis amelie et clara": 1254, " lettre pour caq": 1287, " lettre recommandee desabonnement le monde": 1287, " lettres pour noel pour la famille": 1287, " papiers pour permi etude manquants": 1287}}, "poste canada": {"Company": {"poste canada": 1170}, "Description": {" enveloppes blanches": 1170}}, "poutineville": {"Company": {"poutineville": 3627}, "Description": {" grosse poutine": 1170, " tiphanie": 1170}}, "provigo": {"Company": {"provigo": 7714}, "Description": {" courses": 7714}}, "pub st alexandre": {"Company": {"pub st alexandre": 1287}, "Description": {" biere": 1287}}, "pub u": {"Company": {"pub u": 2424}, "Description": {" ailes de poulet": 1254, " ailes de poulet + biere": 1170}}, "pub universitaire": {"Company": {"pub universitaire": 1170}, "Description": {" soiree": 1170}}, "quebec": {"Company": {"quebec": 1287}, "Description": {" caq": 1287}}, "queue de castor": {"Company": {"queue de castor": 1170}, "Description": {" poutine": 1170}}, "ramq": {"Company": {"ramq": 1247}}, "remboursement": {"Company": {"remboursement": 2457}, "Description": {" aurelien logement new york; ny.19.10": 1170}}, "retrait borne": {"Company": {"retrait borne": 1247}, "Description": {" pour le pauvre qui m a indique le chemin": 1247}}, "rhum": {"Company": {"rhum": 1254}}, "rogers": {"Company": {"rogers": 1287}, "Description": {" ligne telephonique": 1287}}, "rtc": {"Company": {"rtc": 2572}, "Description": {" ticket pour le bus": 2572}}, "rudy s bar": {"Company": {"rudy s bar": 1287}, "Description": {" pizza pate chicago": 1287}}, "saq": {"Company": {"saq": 2340}, "Description": {" alcool": 1170, " vodka et kraken (rhum)": 1170}}, "shogun": {"Company": {"shogun": 1170}, "Description": {" japonais a volonter": 1170}}, "shogun sushi": {"Company": {"shogun sushi": 3859}, "Description": {" jap illimite": 1287, " restaurant": 2572}}, "skream": {"Company": {"skream": 1254}, "Description": {" concert boite nuit electro": 1254}}, "sofitel montreal": {"Company": {"sofitel montreal": 1287}, "Description": {" brunch": 1287}}, "sport expert": {"Company": {"sport expert": 5148}, "Description": {" ": 1287, " bas pour la course et gants en merino": 1287, " corde a sauter et chaussettes course": 1287, " short course": 1287}}, "sport experts": {"Company": {"sport experts": 4874}, "Description": {" chaussures et maillot de bain": 1170, " gourde": 1247, " haut coupe vent et calecons": 1287, " sac course": 1170}}, "starbucks": {"Company": {"starbucks": 1254}, "Description": {" cafe + gateau": 1254}}, "steam": {"Company": {"steam": 5148}, "Description": {" dlc crypt": 1287, " jeu video": 1287, " northgard": 1287, " ratropolis": 1287}}, "studio universal": {"Company": {"studio universal": 1287}, "Description": {" souvenirs": 1287}}, "tacobell": {"Company": {"tacobell": 1254}}, "thinkkitchen": {"Company": {"thinkkitchen": 3627}, "Description": {" equipement": 1170, " fouet, passoire": 1170, " plaque pour gateaux": 1287}}, "tim horton": {"Company": {"tim horton": 1285}, "Description": {" donuts": 1285}}, "uber eats": {"Company": {"uber eats": 1287}, "Description": {" mcdo": 1287}}, "univrac": {"Company": {"univrac": 2574}, "Description": {" fruits secs": 1287, " lentilles et amandes": 1287}}, "walmart": {"Company": {"walmart": 15846}, "Description": {" achat lime a ongle, fil dentaire et ciseau ongle": 1287, " balais": 1287, " bouchons oreilles": 1254, " brosse a dents electrique et couette hiver": 1254, " brosse a dents, crocks, rasoirs": 1170, " courses": 1170, " creme, solaire, coussin, lampe": 1170, " draps + oreiller": 1170, " equipement et affaires scolaires": 1287, " equipement papier cuisson ...": 1170, " preservatifs et lubrifiant": 1287, " provision depart baleines": 1170, " tasse, bol, bouilloire, boule a the, manger": 1170}}, "wendy s": {"Company": {"wendy s": 5075}, "Description": {" avance": 1287}}, "world trade center 1": {"Company": {"world trade center 1": 1254}, "Description": {" visite du dernier etage": 1254}}, "yves rocher": {"Company": {"yves rocher": 1170}, "Description": {" masques": 1170}}, "oqkefqef": {"Company": {"oqkefqef": 1}}}}